argmix_cli/__init__.py
argmix_cli-0.1.0.dist-info/METADATA
argmix_cli-0.1.0.dist-info/WHEEL
argmix_cli-0.1.0.dist-info/top_level.txt
argmix_cli-0.1.0.dist-info/RECORD
