Metadata-Version: 2.4
Name: argmix-cli
Version: 0.1.0
Summary: Coming soon ...
Requires-Python: >=3.9
